Workbook

Sheet Dashboard
B2: FINTECH INDUSTRY OVERVIEW
B5: Industry Analysis Dashboard | Management Presentation
B8: Industry WACC | D8: EV/EBITDA Multiple | F8: P/E Multiple | H8: EV/Revenue Multiple
B9: ='WACC Model'!C27 -> 0.0829161 | D9: ='Industry Multiples'!D5 -> 19.7035 | F9: ='Industry Multiples'!D7 -> 21.018 | H9: ='Industry Multiples'!D6 -> 6.407
B10: Source: WACC Model | D10: Source: Industry Multiples | F10: Source: Industry Multiples | H10: Source: Industry Multiples
B13: Sheet | E13: Description | H13: Key Outputs
B14: WACC Model | E14: Industry Weighted Average Cost of Capital | H14: Cost of Equity, Cost of Debt, WACC
B15: Industry Multiples | E15: Trading & Transaction Multiples | H15: EV/EBITDA, P/E, EV/Revenue, P/B
B16: TAM & CAGR | E16: Total Addressable Market sizing | H16: Market Size, Growth Rates, Projections
B17: Peer Comparison | E17: Benchmarking vs. industry peers | H17: Revenue, Margins, Multiples

Sheet WACC Model
B1: INDUSTRY WACC MODEL
B2: Weighted Average Cost of Capital | Blue = Input | Black = Formula
B4: COST OF EQUITY — Capital Asset Pricing Model (CAPM)
B5: Parameter | C5: Value | D5: Formula / Notes
B6: Risk-Free Rate (Rf) | C6: 0.0435 | D6: 10-Yr US Treasury yield | E6: Source: US Treasury, Mar 2025
B7: Equity Risk Premium (ERP) | C7: 0.055 | D7: Damodaran market ERP | E7: Source: Damodaran, Jan 2025
B8: Beta (β) — Industry Levered | C8: 1.25 | D8: FinTech sector avg. levered beta | E8: Source: Bloomberg consensus
B9: Size Premium | C9: 0.005 | D9: Small-cap adjustment (if applicable)
B10: COST OF EQUITY (Ke) | C10: =C6+C8*C7+C9 -> 0.11725 | D10: Ke = Rf + β × ERP + Size Premium
B12: COST OF DEBT
B13: Parameter | C13: Value | D13: Formula / Notes
B14: Pre-Tax Cost of Debt (Rd) | C14: 0.065 | D14: Industry avg. borrowing rate
B15: Marginal Tax Rate | C15: 0.21 | D15: US Corporate Tax Rate
B16: AFTER-TAX COST OF DEBT (Kd) | C16: =C14*(1-C15) -> 0.05135 | D16: Kd = Pre-Tax Rd × (1 − Tax Rate)
B18: CAPITAL STRUCTURE
B19: Parameter | C19: Value | D19: Formula / Notes
B20: Weight of Equity (E/V) | C20: 0.479 | D20: Equity as % of total capital (industry avg)
B21: Weight of Debt (D/V) | C21: =1-C20 -> 0.521 | D21: Kd(at) x (D/V)
B23: WACC CALCULATION
B24: Parameter | C24: Value | D24: Formula / Notes
B25: Equity Component | C25: =C10*C20 -> 0.05616275 | D25: Ke x (E/V)
B26: Debt Component | C26: =C16*C21 -> 0.02675335 | D26: Kd(at) x (D/V)
B27: INDUSTRY WACC | C27: =C25+C26 -> 0.0829161 | D27: Equity Component + Debt Component
B30: WACC SENSITIVITY — Beta vs. ERP
B31: =C27 -> 0.0829161 | C31: 0.045 | D31: 0.055 | E31: 0.065 | F31: 0.075 | G31: 0.085
B32: 0.9 | C32: 0.06938435 | D32: 0.07369535 | E32: 0.07800635 | F32: 0.08231735 | G32: 0.08662835
B33: 1.05 | C33: 0.0726176 | D33: 0.0776471 | E33: 0.0826766 | F33: 0.0877061 | G33: 0.0927356
B34: 1.2 | C34: 0.07585085 | D34: 0.08159885 | E34: 0.08734685 | F34: 0.09309485 | G34: 0.09884285
B35: 1.35 | C35: 0.0790841 | D35: 0.0855506 | E35: 0.0920171 | F35: 0.0984836 | G35: 0.1049501
B36: 1.5 | C36: 0.08231735 | D36: 0.08950235 | E36: 0.09668735 | F36: 0.10387235 | G36: 0.11105735

Sheet Industry Multiples
B1: INDUSTRY VALUATION MULTIPLES
B3: TRADING MULTIPLES — Current Market
B4: Multiple | C4: Low | D4: Median | E4: High | F4: Notes
B5: EV / EBITDA '24 | C5: ='Peer Comparison'!X17 -> 6.595 | D5: ='Peer Comparison'!X19 -> 19.7035 | E5: ='Peer Comparison'!X20 -> 184.715
B6: EV / Revenue '24 | C6: ='Peer Comparison'!V17 -> 0.495 | D6: ='Peer Comparison'!V19 -> 6.407 | E6: ='Peer Comparison'!V20 -> 31.673
B7: Price / Earnings (P/E) | C7: ='Peer Comparison'!Z17 -> 11.233 | D7: ='Peer Comparison'!Z19 -> 21.018 | E7: ='Peer Comparison'!Z20 -> 135.99 | F7: NTM consensus; excl. unprofitable
B10: TRANSACTION MULTIPLES — M&A Precedent Transactions
B11: Multiple | C11: Low | D11: Median | E11: High | F11: Notes
B12: EV / EBITDA (Acquisitions) | C12: 12 | D12: 20 | E12: 38 | F12: Control premium typically 25-35% over trading
B13: EV / Revenue (Acquisitions) | C13: 3.5 | D13: 7.5 | E13: 25 | F13: High for strategic / synergy-driven deals
B14: Price / Earnings | C14: 22 | D14: 35 | E14: 65 | F14: Premiums on scarcity and strategic fit
B17: Multiple Type | C17: Low | D17: Median | E17: High
B18: EV / EBITDA | C18: 10 | D18: 16.5 | E18: 28
B19: EV / Revenue | C19: 2.5 | D19: 5.8 | E19: 18
B20: Price / Earnings (P/E) | C20: 18 | D20: 28.5 | E20: 55

Sheet TAM & CAGR
B1: TOTAL ADDRESSABLE MARKET (TAM) & CAGR
B3: TAM SNAPSHOT — Addressable Market by Segment (2024E)
B4: Segment | C4: TAM ($T) | D4: CAGR (%) | E4: 2024E ($T) | F4: 2029E ($T) | G4: % of Total TAM | H4: Notes
B5: Global Payments | C5: 2.8 | D5: 0.118 | E5: =C5 -> 2.8 | F5: =C5*(1+D5)^5 -> 4.8906552 | G5: =C5/SUM($C$5:$C$7) -> 0.023931624 | H5: Transaction Volume; includes B2B, B2C, P2P
B6: Consumer Lending | C6: 4.2 | D6: 0.085 | E6: =C6 -> 4.2 | F6: =C6*(1+D6)^5 -> 6.3153581 | G6: =C6/SUM($C$5:$C$7) -> 0.035897436 | H6: Outstanding loans; includes mortgage, personal, auto
B7: Wealth Management | C7: 110 | D7: 0.072 | E7: =C7 -> 110 | F7: =C7*(1+D7)^5 -> 155.72797 | G7: =C7/SUM($C$5:$C$7) -> 0.94017094 | H7: AUM; includes retail, institutional, robo-advisory
B8: TOTAL TAM | C8: =SUM(C5:C7) -> 117 | E8: =SUM(E5:E7) -> 117 | F8: =SUM(F5:F7) -> 166.93398 | G8: 100%
G11: 5-YEAR MARKET PROJECTIONS ($T)
G12: Segment | H12: 2024 | I12: 2025 | J12: 2026 | K12: 2027 | L12: 2028 | M12: 2029
G13: Global Payments | H13: =C5*(1+D5)^0 -> 2.8 | I13: =C5*(1+D5)^1 -> 3.1304 | J13: =C5*(1+D5)^2 -> 3.4997872 | K13: =C5*(1+D5)^3 -> 3.9127621 | L13: =C5*(1+D5)^4 -> 4.374468 | M13: =C5*(1+D5)^5 -> 4.8906552
G14: Consumer Lending | H14: =C6*(1+D6)^0 -> 4.2 | I14: =C6*(1+D6)^1 -> 4.557 | J14: =C6*(1+D6)^2 -> 4.944345 | K14: =C6*(1+D6)^3 -> 5.3646143 | L14: =C6*(1+D6)^4 -> 5.8206065 | M14: =C6*(1+D6)^5 -> 6.3153581
G15: Wealth Management | H15: =C7*(1+D7)^0 -> 110 | I15: =C7*(1+D7)^1 -> 117.92 | J15: =C7*(1+D7)^2 -> 126.41024 | K15: =C7*(1+D7)^3 -> 135.51178 | L15: =C7*(1+D7)^4 -> 145.26863 | M15: =C7*(1+D7)^5 -> 155.72797

Sheet Peer Comparison
B1: PEER COMPARISON — FinTech Industry Benchmarking
B2: Source: Comps Valuation Model (Jan 29, 2026) | 13 FinTech Peers | All figures in $M unless noted | ★ = Subject Company (Fiserv)
B3: COMPANY INFO | H3: FINANCIALS ($M) | O3: GROWTH & MARGINS | U3: TRADING MULTIPLES
B4: Company | C4: Ticker | D4: Sector | E4: Price ($) | F4: Mkt Cap ($M) | G4: EV ($M) | H4: Rev '22 ($M) | I4: Rev '23 ($M) | J4: Rev '24 ($M) | K4: EBITDA '23 ($M) | L4: EBITDA '24 ($M) | M4: Net Inc '23 ($M) | N4: Net Inc '24 ($M) | O4: Rev Grw '23 | P4: Rev Grw '24 | Q4: EBITDA Mgn '23 | R4: EBITDA Mgn '24 | S4: Net Mgn '23 | T4: Net Mgn '24 | U4: EV/Rev '23 | V4: EV/Rev '24 | W4: EV/EBITDA '23 | X4: EV/EBITDA '24 | Y4: P/E '23 | Z4: P/E '24 | AA4: P/B '23 | AB4: P/B '24 | AC4: EV/EBITDA '23 | AD4: EV/EBITDA '24 | AE4: P/E '23 | AF4: P/E '24
B5: Toast | C5: TOST | D5: SaaS / Cloud-based POS & Restaurant Tech | E5: 32 | F5: 18400 | G5: 17497 | H5: 2731 | I5: 3865 | J5: 2731 | K5: -97 | L5: 166 | M5: -241 | N5: 24 | O5: 0.4152 | P5: -0.2934 | Q5: -0.0251 | R5: 0.0608 | S5: -0.0624 | T5: 0.0088 | U5: 4.527 | V5: 6.407 | W5: NM | X5: 105.404 | Y5: NM | Z5: 766.667
B6: Shopify | C6: SHOP | D6: FinTech — Payment processing, SaaS merchant platform | E6: 158.94 | F6: 205798.81 | G6: 205218.81 | H6: 5600 | I6: 7060 | J6: 8880 | K6: -1348 | L6: 1111 | M6: 132 | N6: 2019 | O6: 0.2607 | P6: 0.2578 | Q6: -0.1909 | R6: 0.1251 | S6: 0.0187 | T6: 0.2274 | U6: 29.068 | V6: 23.11 | W6: NM | X6: 184.715 | Y6: 1559.082 | Z6: 101.931
B7: Intuit | C7: INTU | D7: FinTech — QuickBooks, TurboTax, CreditKarma | E7: 654.32 | F7: 183400.66 | G7: 186489.66 | H7: 12726 | I7: 14368 | J7: 16285 | K7: 3934 | L7: 4148 | M7: 2384 | N7: 2963 | O7: 0.129 | P7: 0.1334 | Q7: 0.2738 | R7: 0.2547 | S7: 0.1659 | T7: 0.1819 | U7: 12.98 | V7: 11.452 | W7: 47.405 | X7: 44.959 | Y7: 76.93 | Z7: 61.897
B8: Snowflake | C8: SNOW | D8: Cloud data platform — high-growth SaaS | E8: 271.26 | F8: 90627.97 | G8: 88875.5 | H8: 1219 | I8: 2066 | J8: 2806 | K8: -778.7 | L8: -974.9 | M8: -798 | N8: -838 | O8: 0.6948 | P8: 0.3582 | Q8: -0.3769 | R8: -0.3474 | S8: -0.3863 | T8: -0.2986 | U8: 43.018 | V8: 31.673 | W8: NM | X8: NM | Y8: NM | Z8: NM
B9: PayPal | C9: PYPL | D9: FinTech — Digital payments, wallets, P2P (Venmo, Braintree) | E9: 67.4 | F9: 66674.94 | G9: 68955.94 | H9: 27518 | I9: 29771 | J9: 31797 | K9: 6100 | L9: 6357 | M9: 4246 | N9: 4147 | O9: 0.0819 | P9: 0.0681 | Q9: 0.2049 | R9: 0.1999 | S9: 0.1426 | T9: 0.1304 | U9: 2.316 | V9: 2.169 | W9: 11.304 | X9: 10.847 | Y9: 15.703 | Z9: 16.078
B10: Fiserv ★ | C10: FISV | D10: FinTech — Payment processing, POS systems (Subject Co.) | E10: 64.26 | F10: 36068.43 | G10: 59672.43 | H10: 17737 | I10: 19093 | J10: 20456 | K10: 8176 | L10: 9048 | M10: 3129 | N10: 3211 | O10: 0.0765 | P10: 0.0714 | Q10: 0.4282 | R10: 0.4423 | S10: 0.1639 | T10: 0.157 | U10: 3.125 | V10: 2.917 | W10: 7.298 | X10: 6.595 | Y10: 11.527 | Z10: 11.233
B11: SoFi | C11: SOFI | D11: FinTech — Digital banking, lending, investing | E11: 30.95 | F11: 33937.92 | G11: 35100.92 | H11: 1574 | I11: 2124 | J11: 2677 | K11: -298.5 | L11: 235.6 | M11: -535 | N11: 249.6 | O11: 0.3494 | P11: 0.2604 | Q11: -0.1405 | R11: 0.088 | S11: -0.2519 | T11: 0.0932 | U11: 16.526 | V11: 13.112 | W11: NM | X11: 149.009 | Y11: NM | Z11: 135.99
B12: Affirm | C12: AFRM | D12: FinTech — BNPL, consumer lending | E12: 75.14 | F12: 24469.36 | G12: 29530.58 | H12: 1349 | I12: 1587 | J12: 2322 | K12: 515.8 | L12: 1034 | M12: -985 | N12: -518 | O12: 0.1763 | P12: 0.4631 | Q12: 0.325 | R12: 0.4453 | S12: -0.6207 | T12: -0.2231 | U12: 18.608 | V12: 12.718 | W12: 57.257 | X12: 28.56 | Y12: NM | Z12: NM
B13: Global Payments | C13: GPN | D13: FinTech — Payment processing, software, cloud, issuer solutions | E13: 77.23 | F13: 19123.4 | G13: 32987.4 | H13: 8976 | I13: 9654 | J13: 10106 | K13: 3685 | L13: 4404 | M13: 987 | N13: 1571 | O13: 0.0756 | P13: 0.0468 | Q13: 0.3818 | R13: 0.4358 | S13: 0.1022 | T13: 0.1555 | U13: 3.419 | V13: 3.265 | W13: 8.953 | X13: 7.491 | Y13: 34.053 | Z13: 21.018
B14: Block Inc. | C14: XYZ | D14: FinTech — CashApp, Square POS, Bitcoin, digital wallets | E14: 74.54 | F14: 46176.04 | G14: 11932.91 | H14: 17532 | I14: 21916 | J14: 24121 | K14: -32 | L14: 1115.4 | M14: -21.1 | N14: 2866.5 | O14: 0.25 | P14: 0.1007 | Q14: -0.0015 | R14: 0.0462 | S14: -0.001 | T14: 0.1188 | U14: 0.545 | V14: 0.495 | W14: NM | X14: 10.698 | Y14: NM | Z14: 16.109
B15: Payoneer | C15: PAYO | D15: FinTech — Cross-border B2B payments, SMB platform | E15: 6.23 | F15: 2241.89 | G15: 1744.42 | H15: 628 | I15: 831 | J15: 978 | K15: 131.4 | L15: 196.3 | M15: 93.3 | N15: 121.2 | O15: 0.3237 | P15: 0.1764 | Q15: 0.158 | R15: 0.2008 | S15: 0.1123 | T15: 0.1239 | U15: 2.098 | V15: 1.784 | W15: 13.27 | X15: 8.886 | Y15: 17.753 | Z15: 14.381
B17: Low | U17: =IFERROR(MIN(U3:U15),"-") -> 0.545 | V17: =IFERROR(MIN(V3:V15),"-") -> 0.495 | W17: =IFERROR(MIN(W3:W15),"-") -> 7.298 | X17: =IFERROR(MIN(X3:X15),"-") -> 6.595 | Y17: =IFERROR(MIN(Y3:Y15),"-") -> 11.527 | Z17: =IFERROR(MIN(Z3:Z15),"-") -> 11.233
B18: Mean | U18: =IFERROR(AVERAGEIF(U5:U15,"<>NM",U5:U15),"-") -> 12.384545 | V18: =IFERROR(AVERAGEIF(V5:V15,"<>NM",V5:V15),"-") -> 9.9183636 | W18: =IFERROR(AVERAGEIF(W5:W15,"<>NM",W5:W15),"-") -> 24.247833 | X18: =IFERROR(AVERAGEIF(X5:X15,"<>NM",X5:X15),"-") -> 55.7164 | Y18: =IFERROR(AVERAGEIF(Y5:Y15,"<>NM",Y5:Y15),"-") -> 285.84133 | Z18: =IFERROR(AVERAGEIF(Z5:Z15,"<>NM",Z5:Z15),"-") -> 127.256
B19: Median | E19: - | F19: - | G19: - | H19: - | I19: - | J19: - | K19: - | L19: - | M19: - | N19: - | O19: - | P19: - | Q19: - | R19: - | S19: - | T19: - | U19: =IFERROR(MEDIAN(U5:U15),"-") -> 4.527 | V19: =IFERROR(MEDIAN(V5:V15),"-") -> 6.407 | W19: =IFERROR(MEDIAN(W5:W15),"-") -> 12.287 | X19: =IFERROR(MEDIAN(X5:X15),"-") -> 19.7035 | Y19: =IFERROR(MEDIAN(Y5:Y15),"-") -> 25.903 | Z19: =IFERROR(MEDIAN(Z5:Z15),"-") -> 21.018
B20: High | E20: =IFERROR(PERCENTILE(IF(E5:E15<>"NM",IF(ISNUMBER(E5:E15),E5:E15)),0.75),"-") -> - | F20: =IFERROR(PERCENTILE(IF(F5:F15<>"NM",IF(ISNUMBER(F5:F15),F5:F15)),0.75),"-") -> - | G20: =IFERROR(PERCENTILE(IF(G5:G15<>"NM",IF(ISNUMBER(G5:G15),G5:G15)),0.75),"-") -> - | H20: =IFERROR(PERCENTILE(IF(H5:H15<>"NM",IF(ISNUMBER(H5:H15),H5:H15)),0.75),"-") -> - | I20: =IFERROR(PERCENTILE(IF(I5:I15<>"NM",IF(ISNUMBER(I5:I15),I5:I15)),0.75),"-") -> - | J20: =IFERROR(PERCENTILE(IF(J5:J15<>"NM",IF(ISNUMBER(J5:J15),J5:J15)),0.75),"-") -> - | K20: =IFERROR(PERCENTILE(IF(K5:K15<>"NM",IF(ISNUMBER(K5:K15),K5:K15)),0.75),"-") -> - | L20: =IFERROR(PERCENTILE(IF(L5:L15<>"NM",IF(ISNUMBER(L5:L15),L5:L15)),0.75),"-") -> - | ... T20: =IFERROR(PERCENTILE(IF(T5:T15<>"NM",IF(ISNUMBER(T5:T15),T5:T15)),0.75),"-") -> - | U20: =IFERROR(MAX(U6:U16),"-") -> 43.018 | V20: =IFERROR(MAX(V6:V16),"-") -> 31.673 | W20: =IFERROR(MAX(W6:W16),"-") -> 57.257 | X20: =IFERROR(MAX(X6:X16),"-") -> 184.715 | Y20: =IFERROR(MAX(Y6:Y16),"-") -> 1559.082 | Z20: =IFERROR(MAX(Z6:Z16),"-") -> 135.99
B21: ★ Subject Company (Fiserv) | NM = Not Meaningful (negative EBITDA / loss-making) | Multiples capped for display | Source: Comps Valuation Model, Jan 29 2026
